LICENSE
MANIFEST.in
README.md
setup.py
punter_cli/__init__.py
punter_cli/cli.py
punter_cli/utils.py
punter_cli.egg-info/PKG-INFO
punter_cli.egg-info/SOURCES.txt
punter_cli.egg-info/dependency_links.txt
punter_cli.egg-info/entry_points.txt
punter_cli.egg-info/requires.txt
punter_cli.egg-info/top_level.txt